nssurge_cli/__init__.py
nssurge_cli/cap_commands.py
nssurge_cli/cli.py
nssurge_cli/config.py
nssurge_cli/devices_commands.py
nssurge_cli/dns_commands.py
nssurge_cli/global_commands.py
nssurge_cli/group_commands.py
nssurge_cli/misc_commands.py
nssurge_cli/modules_commands.py
nssurge_cli/outbound_commands.py
nssurge_cli/policy_commands.py
nssurge_cli/profiles_commands.py
nssurge_cli/requests_commands.py
nssurge_cli/scripting_commands.py
nssurge_cli/test_commands.py
nssurge_cli/types.py
nssurge_cli/utils.py
nssurge_cli-2.0.11.dist-info/LICENSE
nssurge_cli-2.0.11.dist-info/METADATA
nssurge_cli-2.0.11.dist-info/WHEEL
nssurge_cli-2.0.11.dist-info/entry_points.txt
nssurge_cli-2.0.11.dist-info/RECORD
