Metadata-Version: 2.1
Name: nssurge-cli
Version: 2.0.11
Summary: NSSurge CLI
Home-page: https://github.com/tddschn/nssurge-cli
License: MIT
Keywords: nssurge,cli,surge,typer
Author: Xinyuan Chen
Author-email: 45612704+tddschn@users.noreply.github.com
Requires-Python: >=3.11,<4.0
Classifier: License :: OSI Approved :: MIT License
Classifier: Programming Language :: Python :: 3
Classifier: Programming Language :: Python :: 3.11
Classifier: Topic :: Utilities
Requires-Dist: nssurge-api (>=0.2.14,<0.3.0)
Requires-Dist: rich[format] (>=12.4.1,<13.0.0)
Requires-Dist: typer (>=0.9.0,<0.10.0)
Requires-Dist: utils-tddschn (>=0.1.5,<0.2.0)
Project-URL: Bug Tracker, https://github.com/tddschn/nssurge-cli/issues
Project-URL: Repository, https://github.com/tddschn/nssurge-cli
